tcrconvert/__init__.py
tcrconvert/build_lookup.py
tcrconvert/cli.py
tcrconvert/convert.py
tcrconvert/utils.py
tcrconvert/data/human/lookup.csv
tcrconvert/data/human/lookup_from_adaptive.csv
tcrconvert/data/human/lookup_from_tenx.csv
tcrconvert/data/mouse/lookup.csv
tcrconvert/data/mouse/lookup_from_adaptive.csv
tcrconvert/data/mouse/lookup_from_tenx.csv
tcrconvert/data/rhesus/lookup.csv
tcrconvert/data/rhesus/lookup_from_adaptive.csv
tcrconvert/data/rhesus/lookup_from_tenx.csv
tcrconvert/examples/adaptive.tsv
tcrconvert/examples/customcols.csv
tcrconvert/examples/imgt.csv
tcrconvert/examples/tenx.csv
tcrconvert/examples/converted/custom2imgt.csv
tcrconvert/examples/converted/imgt2tenx.csv
tcrconvert/examples/converted/tenx2adapt.tsv
tcrconvert/examples/converted/tenx2adapt_rhesus.tsv
tcrconvert/examples/converted/tenx2imgt.csv
tcrconvert/examples/fasta_dir/lookup.csv
tcrconvert/examples/fasta_dir/lookup_from_adaptive.csv
tcrconvert/examples/fasta_dir/lookup_from_tenx.csv
tcrconvert/examples/fasta_dir/test_trav.fa
tcrconvert/examples/fasta_dir/test_trbv.fa
tcrconvert-1.0.dist-info/licenses/LICENSE
tcrconvert-1.0.dist-info/METADATA
tcrconvert-1.0.dist-info/WHEEL
tcrconvert-1.0.dist-info/entry_points.txt
tcrconvert-1.0.dist-info/top_level.txt
tcrconvert-1.0.dist-info/RECORD
