Metadata-Version: 2.4
Name: tcrconvert
Version: 1.0
Summary: Convert TCRs between 10X, Adaptive, and IMGT formats.
Author: Emma Bishop
Author-email: emmab5@uw.edu
License: MIT
Project-URL: Homepage, https://tcrconvert.readthedocs.io/en/latest/
Project-URL: Documentation, https://tcrconvert.readthedocs.io/en/latest/
Project-URL: Repository, https://github.com/seshadrilab/tcrconvert.git
Project-URL: Issues, https://github.com/seshadrilab/tcrconvert/issues
Keywords: TCR,Adaptive,10X,IMGT,T cell receptor,T cell,convert
Classifier: Development Status :: 5 - Production/Stable
Classifier: Intended Audience :: Science/Research
Classifier: Topic :: Scientific/Engineering :: Bio-Informatics
Classifier: License :: OSI Approved :: MIT License
Classifier: Programming Language :: Python :: 3.9
Classifier: Programming Language :: Python :: 3.10
Classifier: Programming Language :: Python :: 3.11
Classifier: Programming Language :: Python :: 3.12
Classifier: Programming Language :: Python :: 3.13
Requires-Python: >=3.9
License-File: LICENSE
Requires-Dist: pandas>=1.5.0
Requires-Dist: click>=8.1.7
Requires-Dist: platformdirs>=4.2.2
Provides-Extra: dev
Requires-Dist: coverage>=7.6.1; extra == "dev"
Requires-Dist: pytest-cov>=5.0.0; extra == "dev"
Requires-Dist: iniconfig>=2.0.0; extra == "dev"
Requires-Dist: pluggy>=1.5.0; extra == "dev"
Requires-Dist: pytest>=8.3.2; extra == "dev"
Provides-Extra: docs
Requires-Dist: packaging>=21.0; extra == "docs"
Requires-Dist: sphinx_rtd_theme>=2.0.0; extra == "docs"
Requires-Dist: tomli>=2.0.1; extra == "docs"
Requires-Dist: nbsphinx>=0.9.5; extra == "docs"
Requires-Dist: ipython>=8.27.0; extra == "docs"
Requires-Dist: ipykernel>=6.29.5; extra == "docs"
Dynamic: license-file
